odoo/addons/purchase_order_invoicing_grouping_criteria/README.rst
odoo/addons/purchase_order_invoicing_grouping_criteria/__init__.py
odoo/addons/purchase_order_invoicing_grouping_criteria/__manifest__.py
odoo/addons/purchase_order_invoicing_grouping_criteria/i18n/es.po
odoo/addons/purchase_order_invoicing_grouping_criteria/i18n/purchase_order_invoicing_grouping_criteria.pot
odoo/addons/purchase_order_invoicing_grouping_criteria/models/__init__.py
odoo/addons/purchase_order_invoicing_grouping_criteria/models/purchase_invoicing_grouping_criteria.py
odoo/addons/purchase_order_invoicing_grouping_criteria/models/purchase_order.py
odoo/addons/purchase_order_invoicing_grouping_criteria/models/res_company.py
odoo/addons/purchase_order_invoicing_grouping_criteria/models/res_config_settings.py
odoo/addons/purchase_order_invoicing_grouping_criteria/models/res_partner.py
odoo/addons/purchase_order_invoicing_grouping_criteria/readme/CONFIGURE.rst
odoo/addons/purchase_order_invoicing_grouping_criteria/readme/CONTRIBUTORS.rst
odoo/addons/purchase_order_invoicing_grouping_criteria/readme/DESCRIPTION.rst
odoo/addons/purchase_order_invoicing_grouping_criteria/readme/USAGE.rst
odoo/addons/purchase_order_invoicing_grouping_criteria/security/ir.model.access.csv
odoo/addons/purchase_order_invoicing_grouping_criteria/static/description/icon.png
odoo/addons/purchase_order_invoicing_grouping_criteria/static/description/index.html
odoo/addons/purchase_order_invoicing_grouping_criteria/tests/__init__.py
odoo/addons/purchase_order_invoicing_grouping_criteria/tests/test_purchase_order_invoicing_group_criteria.py
odoo/addons/purchase_order_invoicing_grouping_criteria/views/purchase_invoicing_grouping_criteria_views.xml
odoo/addons/purchase_order_invoicing_grouping_criteria/views/res_config_settings_views.xml
odoo/addons/purchase_order_invoicing_grouping_criteria/views/res_partner_views.xml
odoo_addon_purchase_order_invoicing_grouping_criteria-15.0.1.0.0.1.dist-info/METADATA
odoo_addon_purchase_order_invoicing_grouping_criteria-15.0.1.0.0.1.dist-info/WHEEL
odoo_addon_purchase_order_invoicing_grouping_criteria-15.0.1.0.0.1.dist-info/top_level.txt
odoo_addon_purchase_order_invoicing_grouping_criteria-15.0.1.0.0.1.dist-info/RECORD
